{
  "commesse_normative": [
    {
      "ramo_id": "ramo_4b24f298b9e3",
      "commessa_id": "comm_1901590d58b5",
      "user_id": "user_97c773827822",
      "normativa": "EN_1090",
      "codice_ramo": "PRV-2026-0003-1090",
      "commessa_base_code": "PRV-2026-0003",
      "branch_type": "EN_1090",
      "line_ids": [],
      "status": "active",
      "created_from": "segmentazione",
      "source_istruttoria_id": "istr_701cc0cc1ddc",
      "source_segmentation_snapshot": null,
      "created_at": "2026-03-22T11:31:59.323695+00:00",
      "updated_at": "2026-03-22T11:32:05.023924+00:00"
    },
    {
      "ramo_id": "ramo_ebca8cb95185",
      "commessa_id": "comm_393ef99b15bd",
      "user_id": "user_97c773827822",
      "normativa": "EN_1090",
      "codice_ramo": "PRV-2026-0003-1090",
      "commessa_base_code": "PRV-2026-0003",
      "branch_type": "EN_1090",
      "line_ids": [],
      "status": "active",
      "created_from": "segmentazione",
      "source_istruttoria_id": "istr_701cc0cc1ddc",
      "source_segmentation_snapshot": null,
      "created_at": "2026-03-22T11:29:41.785846+00:00",
      "updated_at": "2026-03-22T11:31:58.806463+00:00"
    },
    {
      "ramo_id": "ramo_d2517821d055",
      "commessa_id": "comm_a71022d32114",
      "user_id": "user_97c773827822",
      "normativa": "EN_1090",
      "codice_ramo": "PRV-2026-0028-1090",
      "commessa_base_code": "PRV-2026-0028",
      "branch_type": "EN_1090",
      "line_ids": [],
      "status": "active",
      "created_from": "segmentazione",
      "source_istruttoria_id": "istr_21d57d175f49",
      "source_segmentation_snapshot": null,
      "created_at": "2026-03-22T16:19:26.729588+00:00",
      "updated_at": "2026-03-22T16:19:26.729588+00:00"
    },
    {
      "ramo_id": "ramo_0b2ac99468fa",
      "commessa_id": "comm_c73ef8e14598",
      "user_id": "user_97c773827822",
      "normativa": "EN_1090",
      "codice_ramo": "PRV-2026-0003-1090",
      "commessa_base_code": "PRV-2026-0003",
      "branch_type": "EN_1090",
      "line_ids": [],
      "status": "active",
      "created_from": "segmentazione",
      "source_istruttoria_id": "istr_701cc0cc1ddc",
      "source_segmentation_snapshot": null,
      "created_at": "2026-03-22T11:32:05.455310+00:00",
      "updated_at": "2026-03-22T11:32:06.354047+00:00"
    }
  ],
  "obblighi_commessa": [
    {
      "obbligo_id": "obl_9476f58caea4",
      "user_id": "user_6988e9b9316c",
      "tenant_id": null,
      "commessa_id": "com_0cf6badfd12c",
      "cantiere_id": "cant_d96a17088d34",
      "ramo_id": "",
      "emissione_id": "",
      "source_module": "gate_pos",
      "source_entity_type": "cantiere_sicurezza",
      "source_entity_id": "cant_d96a17088d34",
      "code": "POS_INDIRIZZO_CANTIERE",
      "title": "Dato mancante POS: Indirizzo cantiere",
      "description": "Il campo 'Indirizzo cantiere' e obbligatorio per la generazione del POS.",
      "category": "sicurezza",
      "severity": "alta",
      "severity_sort": 1,
      "blocking_level": "hard_block",
      "blocking_level_sort": 1,
      "status": "bloccante",
      "auto_generated": true,
      "owner_role": "sicurezza",
      "owner_user_id": null,
      "due_date": null,
      "linked_route": "/sicurezza/cant_d96a17088d34",
      "linked_label": "Apri scheda cantiere",
      "context": {
        "phase": "sicurezza",
        "gate_type": "gate_pos"
      },
      "dedupe_key": "com_0cf6badfd12c|gate_pos|cant_d96a17088d34|POS_INDIRIZZO_CANTIERE",
      "created_at": "2026-03-22T17:47:09.243602+00:00",
      "updated_at": "2026-03-22T17:47:09.243602+00:00",
      "resolved_at": null,
      "resolved_by": null,
      "resolution_note": null
    },
    {
      "obbligo_id": "obl_21760dd9916a",
      "user_id": "user_6988e9b9316c",
      "tenant_id": null,
      "commessa_id": "com_0cf6badfd12c",
      "cantiere_id": "cant_d96a17088d34",
      "ramo_id": "",
      "emissione_id": "",
      "source_module": "gate_pos",
      "source_entity_type": "cantiere_sicurezza",
      "source_entity_id": "cant_d96a17088d34",
      "code": "POS_CITTA_CANTIERE",
      "title": "Dato mancante POS: Citta cantiere",
      "description": "Il campo 'Citta cantiere' e obbligatorio per la generazione del POS.",
      "category": "sicurezza",
      "severity": "alta",
      "severity_sort": 1,
      "blocking_level": "hard_block",
      "blocking_level_sort": 1,
      "status": "bloccante",
      "auto_generated": true,
      "owner_role": "sicurezza",
      "owner_user_id": null,
      "due_date": null,
      "linked_route": "/sicurezza/cant_d96a17088d34",
      "linked_label": "Apri scheda cantiere",
      "context": {
        "phase": "sicurezza",
        "gate_type": "gate_pos"
      },
      "dedupe_key": "com_0cf6badfd12c|gate_pos|cant_d96a17088d34|POS_CITTA_CANTIERE",
      "created_at": "2026-03-22T17:47:09.243628+00:00",
      "updated_at": "2026-03-22T17:47:09.243628+00:00",
      "resolved_at": null,
      "resolved_by": null,
      "resolution_note": null
    },
    {
      "obbligo_id": "obl_8a34d715b02a",
      "user_id": "user_6988e9b9316c",
      "tenant_id": null,
      "commessa_id": "com_0cf6badfd12c",
      "cantiere_id": "cant_d96a17088d34",
      "ramo_id": "",
      "emissione_id": "",
      "source_module": "gate_pos",
      "source_entity_type": "cantiere_sicurezza",
      "source_entity_id": "cant_d96a17088d34",
      "code": "POS_DATA_INIZIO_LAVORI",
      "title": "Dato mancante POS: Data inizio lavori",
      "description": "Il campo 'Data inizio lavori' e obbligatorio per la generazione del POS.",
      "category": "sicurezza",
      "severity": "alta",
      "severity_sort": 1,
      "blocking_level": "hard_block",
      "blocking_level_sort": 1,
      "status": "bloccante",
      "auto_generated": true,
      "owner_role": "sicurezza",
      "owner_user_id": null,
      "due_date": null,
      "linked_route": "/sicurezza/cant_d96a17088d34",
      "linked_label": "Apri scheda cantiere",
      "context": {
        "phase": "sicurezza",
        "gate_type": "gate_pos"
      },
      "dedupe_key": "com_0cf6badfd12c|gate_pos|cant_d96a17088d34|POS_DATA_INIZIO_LAVORI",
      "created_at": "2026-03-22T17:47:09.243637+00:00",
      "updated_at": "2026-03-22T17:47:09.243637+00:00",
      "resolved_at": null,
      "resolved_by": null,
      "resolution_note": null
    },
    {
      "obbligo_id": "obl_96e8e1bd9bdd",
      "user_id": "user_6988e9b9316c",
      "tenant_id": null,
      "commessa_id": "com_0cf6badfd12c",
      "cantiere_id": "cant_d96a17088d34",
      "ramo_id": "",
      "emissione_id": "",
      "source_module": "gate_pos",
      "source_entity_type": "cantiere_sicurezza",
      "source_entity_id": "cant_d96a17088d34",
      "code": "POS_ALMENO_UN_LAVORATORE",
      "title": "Dato mancante POS: Almeno un lavoratore",
      "description": "Il campo 'Almeno un lavoratore' e obbligatorio per la generazione del POS.",
      "category": "sicurezza",
      "severity": "alta",
      "severity_sort": 1,
      "blocking_level": "hard_block",
      "blocking_level_sort": 1,
      "status": "bloccante",
      "auto_generated": true,
      "owner_role": "sicurezza",
      "owner_user_id": null,
      "due_date": null,
      "linked_route": "/sicurezza/cant_d96a17088d34",
      "linked_label": "Apri scheda cantiere",
      "context": {
        "phase": "sicurezza",
        "gate_type": "gate_pos"
      },
      "dedupe_key": "com_0cf6badfd12c|gate_pos|cant_d96a17088d34|POS_ALMENO_UN_LAVORATORE",
      "created_at": "2026-03-22T17:47:09.243648+00:00",
      "updated_at": "2026-03-22T17:47:09.243648+00:00",
      "resolved_at": null,
      "resolved_by": null,
      "resolution_note": null
    },
    {
      "obbligo_id": "obl_faada46f0fdc",
      "user_id": "user_6988e9b9316c",
      "tenant_id": null,
      "commessa_id": "com_0cf6badfd12c",
      "cantiere_id": "cant_d96a17088d34",
      "ramo_id": "",
      "emissione_id": "",
      "source_module": "gate_pos",
      "source_entity_type": "cantiere_sicurezza",
      "source_entity_id": "cant_d96a17088d34",
      "code": "POS_ALMENO_UNA_FASE_DI_LAVORO",
      "title": "Dato mancante POS: Almeno una fase di lavoro",
      "description": "Il campo 'Almeno una fase di lavoro' e obbligatorio per la generazione del POS.",
      "category": "sicurezza",
      "severity": "alta",
      "severity_sort": 1,
      "blocking_level": "hard_block",
      "blocking_level_sort": 1,
      "status": "bloccante",
      "auto_generated": true,
      "owner_role": "sicurezza",
      "owner_user_id": null,
      "due_date": null,
      "linked_route": "/sicurezza/cant_d96a17088d34",
      "linked_label": "Apri scheda cantiere",
      "context": {
        "phase": "sicurezza",
        "gate_type": "gate_pos"
      },
      "dedupe_key": "com_0cf6badfd12c|gate_pos|cant_d96a17088d34|POS_ALMENO_UNA_FASE_DI_LAVORO",
      "created_at": "2026-03-22T17:47:09.243659+00:00",
      "updated_at": "2026-03-22T17:47:09.243659+00:00",
      "resolved_at": null,
      "resolved_by": null,
      "resolution_note": null
    },
    {
      "obbligo_id": "obl_61aed5180486",
      "user_id": "user_6988e9b9316c",
      "tenant_id": null,
      "commessa_id": "com_0cf6badfd12c",
      "cantiere_id": "cant_d96a17088d34",
      "ramo_id": "",
      "emissione_id": "",
      "source_module": "gate_pos",
      "source_entity_type": "cantiere_sicurezza",
      "source_entity_id": "cant_d96a17088d34",
      "code": "POS_SOGGETTO__COMMITTENTE",
      "title": "Dato mancante POS: Soggetto: Committente",
      "description": "Il campo 'Soggetto: Committente' e obbligatorio per la generazione del POS.",
      "category": "sicurezza",
      "severity": "alta",
      "severity_sort": 1,
      "blocking_level": "hard_block",
      "blocking_level_sort": 1,
      "status": "bloccante",
      "auto_generated": true,
      "owner_role": "sicurezza",
      "owner_user_id": null,
      "due_date": null,
      "linked_route": "/sicurezza/cant_d96a17088d34",
      "linked_label": "Apri scheda cantiere",
      "context": {
        "phase": "sicurezza",
        "gate_type": "gate_pos"
      },
      "dedupe_key": "com_0cf6badfd12c|gate_pos|cant_d96a17088d34|POS_SOGGETTO__COMMITTENTE",
      "created_at": "2026-03-22T17:47:09.243675+00:00",
      "updated_at": "2026-03-22T17:47:09.243675+00:00",
      "resolved_at": null,
      "resolved_by": null,
      "resolution_note": null
    },
    {
      "obbligo_id": "obl_257824995807",
      "user_id": "user_6988e9b9316c",
      "tenant_id": null,
      "commessa_id": "com_0cf6badfd12c",
      "cantiere_id": "cant_d96a17088d34",
      "ramo_id": "",
      "emissione_id": "",
      "source_module": "soggetti",
      "source_entity_type": "cantiere_sicurezza",
      "source_entity_id": "cant_d96a17088d34",
      "code": "COMMITTENTE_MISSING",
      "title": "Committente non indicato",
      "description": "Il ruolo obbligatorio 'Committente' non risulta compilato nella scheda cantiere.",
      "category": "soggetti",
      "severity": "alta",
      "severity_sort": 1,
      "blocking_level": "hard_block",
      "blocking_level_sort": 1,
      "status": "bloccante",
      "auto_generated": true,
      "owner_role": "sicurezza",
      "owner_user_id": null,
      "due_date": null,
      "linked_route": "/sicurezza/cant_d96a17088d34",
      "linked_label": "Apri scheda cantiere",
      "context": {
        "phase": "sicurezza",
        "gate_type": "soggetti"
      },
      "dedupe_key": "com_0cf6badfd12c|soggetti|cant_d96a17088d34|COMMITTENTE_MISSING",
      "created_at": "2026-03-22T17:47:09.244043+00:00",
      "updated_at": "2026-03-22T17:47:09.244043+00:00",
      "resolved_at": null,
      "resolved_by": null,
      "resolution_note": null
    },
    {
      "obbligo_id": "obl_5c70df2cc87a",
      "user_id": "user_6988e9b9316c",
      "tenant_id": null,
      "commessa_id": "com_0cf6badfd12c",
      "cantiere_id": "cant_d96a17088d34",
      "ramo_id": "",
      "emissione_id": "",
      "source_module": "gate_pos",
      "source_entity_type": "cantiere_sicurezza",
      "source_entity_id": "cant_d96a17088d34",
      "code": "POS_SOGGETTO__RSPP",
      "title": "Dato mancante POS: Soggetto: Rspp",
      "description": "Il campo 'Soggetto: Rspp' e obbligatorio per la generazione del POS.",
      "category": "sicurezza",
      "severity": "alta",
      "severity_sort": 1,
      "blocking_level": "hard_block",
      "blocking_level_sort": 1,
      "status": "completato",
      "auto_generated": true,
      "owner_role": "sicurezza",
      "owner_user_id": null,
      "due_date": null,
      "linked_route": "/sicurezza/cant_d96a17088d34",
      "linked_label": "Apri scheda cantiere",
      "context": {
        "phase": "sicurezza",
        "gate_type": "gate_pos"
      },
      "dedupe_key": "com_0cf6badfd12c|gate_pos|cant_d96a17088d34|POS_SOGGETTO__RSPP",
      "created_at": "2026-03-22T17:47:09.243667+00:00",
      "updated_at": "2026-03-22T17:47:18.994082+00:00",
      "resolved_at": "2026-03-22T17:47:18.994082+00:00",
      "resolved_by": null,
      "resolution_note": "Chiuso automaticamente: condizione non piu presente nella fonte gate_pos"
    },
    {
      "obbligo_id": "obl_430c6b4f4814",
      "user_id": "user_6988e9b9316c",
      "tenant_id": null,
      "commessa_id": "com_0cf6badfd12c",
      "cantiere_id": "cant_d96a17088d34",
      "ramo_id": "",
      "emissione_id": "",
      "source_module": "soggetti",
      "source_entity_type": "cantiere_sicurezza",
      "source_entity_id": "cant_d96a17088d34",
      "code": "RSPP_MISSING",
      "title": "RSPP non indicato",
      "description": "Il ruolo obbligatorio 'RSPP' non risulta compilato nella scheda cantiere.",
      "category": "sicurezza",
      "severity": "alta",
      "severity_sort": 1,
      "blocking_level": "hard_block",
      "blocking_level_sort": 1,
      "status": "completato",
      "auto_generated": true,
      "owner_role": "sicurezza",
      "owner_user_id": null,
      "due_date": null,
      "linked_route": "/sicurezza/cant_d96a17088d34",
      "linked_label": "Apri scheda cantiere",
      "context": {
        "phase": "sicurezza",
        "gate_type": "soggetti"
      },
      "dedupe_key": "com_0cf6badfd12c|soggetti|cant_d96a17088d34|RSPP_MISSING",
      "created_at": "2026-03-22T17:47:09.244030+00:00",
      "updated_at": "2026-03-22T17:47:18.994082+00:00",
      "resolved_at": "2026-03-22T17:47:18.994082+00:00",
      "resolved_by": null,
      "resolution_note": "Chiuso automaticamente: condizione non piu presente nella fonte soggetti"
    },
    {
      "obbligo_id": "obl_9ed1ed63c2bf",
      "user_id": "user_6988e9b9316c",
      "tenant_id": null,
      "commessa_id": "com_0cf6badfd12c",
      "cantiere_id": "cant_d96a17088d34",
      "ramo_id": "",
      "emissione_id": "",
      "source_module": "soggetti",
      "source_entity_type": "cantiere_sicurezza",
      "source_entity_id": "cant_d96a17088d34",
      "code": "MEDICO_COMPETENTE_MISSING",
      "title": "Medico Competente non indicato",
      "description": "Il ruolo obbligatorio 'Medico Competente' non risulta compilato nella scheda cantiere.",
      "category": "sicurezza",
      "severity": "media",
      "severity_sort": 2,
      "blocking_level": "warning",
      "blocking_level_sort": 2,
      "status": "nuovo",
      "auto_generated": true,
      "owner_role": "sicurezza",
      "owner_user_id": null,
      "due_date": null,
      "linked_route": "/sicurezza/cant_d96a17088d34",
      "linked_label": "Apri scheda cantiere",
      "context": {
        "phase": "sicurezza",
        "gate_type": "soggetti"
      },
      "dedupe_key": "com_0cf6badfd12c|soggetti|cant_d96a17088d34|MEDICO_COMPETENTE_MISSING",
      "created_at": "2026-03-22T17:47:09.244052+00:00",
      "updated_at": "2026-03-22T17:47:09.244052+00:00",
      "resolved_at": null,
      "resolved_by": null,
      "resolution_note": null
    },
    {
      "obbligo_id": "obl_27116c25295c",
      "user_id": "user_6988e9b9316c",
      "tenant_id": null,
      "commessa_id": "com_0cf6badfd12c",
      "cantiere_id": "cant_d96a17088d34",
      "ramo_id": "",
      "emissione_id": "",
      "source_module": "soggetti",
      "source_entity_type": "cantiere_sicurezza",
      "source_entity_id": "cant_d96a17088d34",
      "code": "PREPOSTO_CANTIERE_MISSING",
      "title": "Preposto Cantiere non indicato",
      "description": "Il ruolo obbligatorio 'Preposto Cantiere' non risulta compilato nella scheda cantiere.",
      "category": "sicurezza",
      "severity": "media",
      "severity_sort": 2,
      "blocking_level": "warning",
      "blocking_level_sort": 2,
      "status": "nuovo",
      "auto_generated": true,
      "owner_role": "sicurezza",
      "owner_user_id": null,
      "due_date": null,
      "linked_route": "/sicurezza/cant_d96a17088d34",
      "linked_label": "Apri scheda cantiere",
      "context": {
        "phase": "sicurezza",
        "gate_type": "soggetti"
      },
      "dedupe_key": "com_0cf6badfd12c|soggetti|cant_d96a17088d34|PREPOSTO_CANTIERE_MISSING",
      "created_at": "2026-03-22T17:47:09.244059+00:00",
      "updated_at": "2026-03-22T17:47:09.244059+00:00",
      "resolved_at": null,
      "resolved_by": null,
      "resolution_note": null
    },
    {
      "obbligo_id": "obl_156e1c5f2475",
      "user_id": "user_6988e9b9316c",
      "tenant_id": null,
      "commessa_id": "com_7295fcc4e93c",
      "cantiere_id": "cant_4c55c12507fb",
      "ramo_id": "",
      "emissione_id": "",
      "source_module": "gate_pos",
      "source_entity_type": "cantiere_sicurezza",
      "source_entity_id": "cant_4c55c12507fb",
      "code": "POS_INDIRIZZO_CANTIERE",
      "title": "Dato mancante POS: Indirizzo cantiere",
      "description": "Il campo 'Indirizzo cantiere' e obbligatorio per la generazione del POS.",
      "category": "sicurezza",
      "severity": "alta",
      "severity_sort": 1,
      "blocking_level": "hard_block",
      "blocking_level_sort": 1,
      "status": "bloccante",
      "auto_generated": true,
      "owner_role": "sicurezza",
      "owner_user_id": null,
      "due_date": null,
      "linked_route": "/sicurezza/cant_4c55c12507fb",
      "linked_label": "Apri scheda cantiere",
      "context": {
        "phase": "sicurezza",
        "gate_type": "gate_pos"
      },
      "dedupe_key": "com_7295fcc4e93c|gate_pos|cant_4c55c12507fb|POS_INDIRIZZO_CANTIERE",
      "created_at": "2026-03-22T17:47:28.659350+00:00",
      "updated_at": "2026-03-22T17:47:28.659350+00:00",
      "resolved_at": null,
      "resolved_by": null,
      "resolution_note": null
    },
    {
      "obbligo_id": "obl_a6a50c45a346",
      "user_id": "user_6988e9b9316c",
      "tenant_id": null,
      "commessa_id": "com_7295fcc4e93c",
      "cantiere_id": "cant_4c55c12507fb",
      "ramo_id": "",
      "emissione_id": "",
      "source_module": "gate_pos",
      "source_entity_type": "cantiere_sicurezza",
      "source_entity_id": "cant_4c55c12507fb",
      "code": "POS_CITTA_CANTIERE",
      "title": "Dato mancante POS: Citta cantiere",
      "description": "Il campo 'Citta cantiere' e obbligatorio per la generazione del POS.",
      "category": "sicurezza",
      "severity": "alta",
      "severity_sort": 1,
      "blocking_level": "hard_block",
      "blocking_level_sort": 1,
      "status": "bloccante",
      "auto_generated": true,
      "owner_role": "sicurezza",
      "owner_user_id": null,
      "due_date": null,
      "linked_route": "/sicurezza/cant_4c55c12507fb",
      "linked_label": "Apri scheda cantiere",
      "context": {
        "phase": "sicurezza",
        "gate_type": "gate_pos"
      },
      "dedupe_key": "com_7295fcc4e93c|gate_pos|cant_4c55c12507fb|POS_CITTA_CANTIERE",
      "created_at": "2026-03-22T17:47:28.659378+00:00",
      "updated_at": "2026-03-22T17:47:28.659378+00:00",
      "resolved_at": null,
      "resolved_by": null,
      "resolution_note": null
    },
    {
      "obbligo_id": "obl_88b69cfff200",
      "user_id": "user_6988e9b9316c",
      "tenant_id": null,
      "commessa_id": "com_7295fcc4e93c",
      "cantiere_id": "cant_4c55c12507fb",
      "ramo_id": "",
      "emissione_id": "",
      "source_module": "gate_pos",
      "source_entity_type": "cantiere_sicurezza",
      "source_entity_id": "cant_4c55c12507fb",
      "code": "POS_DATA_INIZIO_LAVORI",
      "title": "Dato mancante POS: Data inizio lavori",
      "description": "Il campo 'Data inizio lavori' e obbligatorio per la generazione del POS.",
      "category": "sicurezza",
      "severity": "alta",
      "severity_sort": 1,
      "blocking_level": "hard_block",
      "blocking_level_sort": 1,
      "status": "bloccante",
      "auto_generated": true,
      "owner_role": "sicurezza",
      "owner_user_id": null,
      "due_date": null,
      "linked_route": "/sicurezza/cant_4c55c12507fb",
      "linked_label": "Apri scheda cantiere",
      "context": {
        "phase": "sicurezza",
        "gate_type": "gate_pos"
      },
      "dedupe_key": "com_7295fcc4e93c|gate_pos|cant_4c55c12507fb|POS_DATA_INIZIO_LAVORI",
      "created_at": "2026-03-22T17:47:28.659391+00:00",
      "updated_at": "2026-03-22T17:47:28.659391+00:00",
      "resolved_at": null,
      "resolved_by": null,
      "resolution_note": null
    },
    {
      "obbligo_id": "obl_56d82449d2d7",
      "user_id": "user_6988e9b9316c",
      "tenant_id": null,
      "commessa_id": "com_7295fcc4e93c",
      "cantiere_id": "cant_4c55c12507fb",
      "ramo_id": "",
      "emissione_id": "",
      "source_module": "gate_pos",
      "source_entity_type": "cantiere_sicurezza",
      "source_entity_id": "cant_4c55c12507fb",
      "code": "POS_ALMENO_UN_LAVORATORE",
      "title": "Dato mancante POS: Almeno un lavoratore",
      "description": "Il campo 'Almeno un lavoratore' e obbligatorio per la generazione del POS.",
      "category": "sicurezza",
      "severity": "alta",
      "severity_sort": 1,
      "blocking_level": "hard_block",
      "blocking_level_sort": 1,
      "status": "bloccante",
      "auto_generated": true,
      "owner_role": "sicurezza",
      "owner_user_id": null,
      "due_date": null,
      "linked_route": "/sicurezza/cant_4c55c12507fb",
      "linked_label": "Apri scheda cantiere",
      "context": {
        "phase": "sicurezza",
        "gate_type": "gate_pos"
      },
      "dedupe_key": "com_7295fcc4e93c|gate_pos|cant_4c55c12507fb|POS_ALMENO_UN_LAVORATORE",
      "created_at": "2026-03-22T17:47:28.659397+00:00",
      "updated_at": "2026-03-22T17:47:28.659397+00:00",
      "resolved_at": null,
      "resolved_by": null,
      "resolution_note": null
    },
    {
      "obbligo_id": "obl_29a067bc0359",
      "user_id": "user_6988e9b9316c",
      "tenant_id": null,
      "commessa_id": "com_7295fcc4e93c",
      "cantiere_id": "cant_4c55c12507fb",
      "ramo_id": "",
      "emissione_id": "",
      "source_module": "gate_pos",
      "source_entity_type": "cantiere_sicurezza",
      "source_entity_id": "cant_4c55c12507fb",
      "code": "POS_ALMENO_UNA_FASE_DI_LAVORO",
      "title": "Dato mancante POS: Almeno una fase di lavoro",
      "description": "Il campo 'Almeno una fase di lavoro' e obbligatorio per la generazione del POS.",
      "category": "sicurezza",
      "severity": "alta",
      "severity_sort": 1,
      "blocking_level": "hard_block",
      "blocking_level_sort": 1,
      "status": "bloccante",
      "auto_generated": true,
      "owner_role": "sicurezza",
      "owner_user_id": null,
      "due_date": null,
      "linked_route": "/sicurezza/cant_4c55c12507fb",
      "linked_label": "Apri scheda cantiere",
      "context": {
        "phase": "sicurezza",
        "gate_type": "gate_pos"
      },
      "dedupe_key": "com_7295fcc4e93c|gate_pos|cant_4c55c12507fb|POS_ALMENO_UNA_FASE_DI_LAVORO",
      "created_at": "2026-03-22T17:47:28.659403+00:00",
      "updated_at": "2026-03-22T17:47:28.659403+00:00",
      "resolved_at": null,
      "resolved_by": null,
      "resolution_note": null
    },
    {
      "obbligo_id": "obl_5b8ed3abc599",
      "user_id": "user_6988e9b9316c",
      "tenant_id": null,
      "commessa_id": "com_7295fcc4e93c",
      "cantiere_id": "cant_4c55c12507fb",
      "ramo_id": "",
      "emissione_id": "",
      "source_module": "gate_pos",
      "source_entity_type": "cantiere_sicurezza",
      "source_entity_id": "cant_4c55c12507fb",
      "code": "POS_SOGGETTO__RSPP",
      "title": "Dato mancante POS: Soggetto: Rspp",
      "description": "Il campo 'Soggetto: Rspp' e obbligatorio per la generazione del POS.",
      "category": "sicurezza",
      "severity": "alta",
      "severity_sort": 1,
      "blocking_level": "hard_block",
      "blocking_level_sort": 1,
      "status": "bloccante",
      "auto_generated": true,
      "owner_role": "sicurezza",
      "owner_user_id": null,
      "due_date": null,
      "linked_route": "/sicurezza/cant_4c55c12507fb",
      "linked_label": "Apri scheda cantiere",
      "context": {
        "phase": "sicurezza",
        "gate_type": "gate_pos"
      },
      "dedupe_key": "com_7295fcc4e93c|gate_pos|cant_4c55c12507fb|POS_SOGGETTO__RSPP",
      "created_at": "2026-03-22T17:47:28.659415+00:00",
      "updated_at": "2026-03-22T17:47:42.925976+00:00",
      "resolved_at": null,
      "resolved_by": null,
      "resolution_note": null
    },
    {
      "obbligo_id": "obl_071d8ed53800",
      "user_id": "user_6988e9b9316c",
      "tenant_id": null,
      "commessa_id": "com_7295fcc4e93c",
      "cantiere_id": "cant_4c55c12507fb",
      "ramo_id": "",
      "emissione_id": "",
      "source_module": "gate_pos",
      "source_entity_type": "cantiere_sicurezza",
      "source_entity_id": "cant_4c55c12507fb",
      "code": "POS_SOGGETTO__COMMITTENTE",
      "title": "Dato mancante POS: Soggetto: Committente",
      "description": "Il campo 'Soggetto: Committente' e obbligatorio per la generazione del POS.",
      "category": "sicurezza",
      "severity": "alta",
      "severity_sort": 1,
      "blocking_level": "hard_block",
      "blocking_level_sort": 1,
      "status": "bloccante",
      "auto_generated": true,
      "owner_role": "sicurezza",
      "owner_user_id": null,
      "due_date": null,
      "linked_route": "/sicurezza/cant_4c55c12507fb",
      "linked_label": "Apri scheda cantiere",
      "context": {
        "phase": "sicurezza",
        "gate_type": "gate_pos"
      },
      "dedupe_key": "com_7295fcc4e93c|gate_pos|cant_4c55c12507fb|POS_SOGGETTO__COMMITTENTE",
      "created_at": "2026-03-22T17:47:28.659421+00:00",
      "updated_at": "2026-03-22T17:47:28.659421+00:00",
      "resolved_at": null,
      "resolved_by": null,
      "resolution_note": null
    },
    {
      "obbligo_id": "obl_3ef0dda12e6f",
      "user_id": "user_6988e9b9316c",
      "tenant_id": null,
      "commessa_id": "com_7295fcc4e93c",
      "cantiere_id": "cant_4c55c12507fb",
      "ramo_id": "",
      "emissione_id": "",
      "source_module": "soggetti",
      "source_entity_type": "cantiere_sicurezza",
      "source_entity_id": "cant_4c55c12507fb",
      "code": "RSPP_MISSING",
      "title": "RSPP non indicato",
      "description": "Il ruolo obbligatorio 'RSPP' non risulta compilato nella scheda cantiere.",
      "category": "sicurezza",
      "severity": "alta",
      "severity_sort": 1,
      "blocking_level": "hard_block",
      "blocking_level_sort": 1,
      "status": "bloccante",
      "auto_generated": true,
      "owner_role": "sicurezza",
      "owner_user_id": null,
      "due_date": null,
      "linked_route": "/sicurezza/cant_4c55c12507fb",
      "linked_label": "Apri scheda cantiere",
      "context": {
        "phase": "sicurezza",
        "gate_type": "soggetti"
      },
      "dedupe_key": "com_7295fcc4e93c|soggetti|cant_4c55c12507fb|RSPP_MISSING",
      "created_at": "2026-03-22T17:47:28.660132+00:00",
      "updated_at": "2026-03-22T17:47:42.925976+00:00",
      "resolved_at": null,
      "resolved_by": null,
      "resolution_note": null
    },
    {
      "obbligo_id": "obl_2b507c14fc78",
      "user_id": "user_6988e9b9316c",
      "tenant_id": null,
      "commessa_id": "com_7295fcc4e93c",
      "cantiere_id": "cant_4c55c12507fb",
      "ramo_id": "",
      "emissione_id": "",
      "source_module": "soggetti",
      "source_entity_type": "cantiere_sicurezza",
      "source_entity_id": "cant_4c55c12507fb",
      "code": "COMMITTENTE_MISSING",
      "title": "Committente non indicato",
      "description": "Il ruolo obbligatorio 'Committente' non risulta compilato nella scheda cantiere.",
      "category": "soggetti",
      "severity": "alta",
      "severity_sort": 1,
      "blocking_level": "hard_block",
      "blocking_level_sort": 1,
      "status": "bloccante",
      "auto_generated": true,
      "owner_role": "sicurezza",
      "owner_user_id": null,
      "due_date": null,
      "linked_route": "/sicurezza/cant_4c55c12507fb",
      "linked_label": "Apri scheda cantiere",
      "context": {
        "phase": "sicurezza",
        "gate_type": "soggetti"
      },
      "dedupe_key": "com_7295fcc4e93c|soggetti|cant_4c55c12507fb|COMMITTENTE_MISSING",
      "created_at": "2026-03-22T17:47:28.660150+00:00",
      "updated_at": "2026-03-22T17:47:28.660150+00:00",
      "resolved_at": null,
      "resolved_by": null,
      "resolution_note": null
    },
    {
      "obbligo_id": "obl_f44a339d7393",
      "user_id": "user_6988e9b9316c",
      "tenant_id": null,
      "commessa_id": "com_7295fcc4e93c",
      "cantiere_id": "cant_4c55c12507fb",
      "ramo_id": "",
      "emissione_id": "",
      "source_module": "gate_pos",
      "source_entity_type": "cantiere_sicurezza",
      "source_entity_id": "cant_4c55c12507fb",
      "code": "POS_SOGGETTO__DATORE_LAVORO",
      "title": "Dato mancante POS: Soggetto: Datore Lavoro",
      "description": "Il campo 'Soggetto: Datore Lavoro' e obbligatorio per la generazione del POS.",
      "category": "sicurezza",
      "severity": "alta",
      "severity_sort": 1,
      "blocking_level": "hard_block",
      "blocking_level_sort": 1,
      "status": "bloccante",
      "auto_generated": true,
      "owner_role": "sicurezza",
      "owner_user_id": null,
      "due_date": null,
      "linked_route": "/sicurezza/cant_4c55c12507fb",
      "linked_label": "Apri scheda cantiere",
      "context": {
        "phase": "sicurezza",
        "gate_type": "gate_pos"
      },
      "dedupe_key": "com_7295fcc4e93c|gate_pos|cant_4c55c12507fb|POS_SOGGETTO__DATORE_LAVORO",
      "created_at": "2026-03-22T17:47:35.381402+00:00",
      "updated_at": "2026-03-22T17:47:35.381402+00:00",
      "resolved_at": null,
      "resolved_by": null,
      "resolution_note": null
    },
    {
      "obbligo_id": "obl_7c3efc7c987b",
      "user_id": "user_6988e9b9316c",
      "tenant_id": null,
      "commessa_id": "com_7295fcc4e93c",
      "cantiere_id": "cant_4c55c12507fb",
      "ramo_id": "",
      "emissione_id": "",
      "source_module": "soggetti",
      "source_entity_type": "cantiere_sicurezza",
      "source_entity_id": "cant_4c55c12507fb",
      "code": "DATORE_LAVORO_MISSING",
      "title": "Datore di Lavoro non indicato",
      "description": "Il ruolo obbligatorio 'Datore di Lavoro' non risulta compilato nella scheda cantiere.",
      "category": "sicurezza",
      "severity": "alta",
      "severity_sort": 1,
      "blocking_level": "hard_block",
      "blocking_level_sort": 1,
      "status": "bloccante",
      "auto_generated": true,
      "owner_role": "sicurezza",
      "owner_user_id": null,
      "due_date": null,
      "linked_route": "/sicurezza/cant_4c55c12507fb",
      "linked_label": "Apri scheda cantiere",
      "context": {
        "phase": "sicurezza",
        "gate_type": "soggetti"
      },
      "dedupe_key": "com_7295fcc4e93c|soggetti|cant_4c55c12507fb|DATORE_LAVORO_MISSING",
      "created_at": "2026-03-22T17:47:35.381867+00:00",
      "updated_at": "2026-03-22T17:47:35.381867+00:00",
      "resolved_at": null,
      "resolved_by": null,
      "resolution_note": null
    },
    {
      "obbligo_id": "obl_1e5e8890bc31",
      "user_id": "user_6988e9b9316c",
      "tenant_id": null,
      "commessa_id": "com_7295fcc4e93c",
      "cantiere_id": "cant_4c55c12507fb",
      "ramo_id": "",
      "emissione_id": "",
      "source_module": "soggetti",
      "source_entity_type": "cantiere_sicurezza",
      "source_entity_id": "cant_4c55c12507fb",
      "code": "MEDICO_COMPETENTE_MISSING",
      "title": "Medico Competente non indicato",
      "description": "Il ruolo obbligatorio 'Medico Competente' non risulta compilato nella scheda cantiere.",
      "category": "sicurezza",
      "severity": "media",
      "severity_sort": 2,
      "blocking_level": "warning",
      "blocking_level_sort": 2,
      "status": "completato",
      "auto_generated": true,
      "owner_role": "sicurezza",
      "owner_user_id": null,
      "due_date": null,
      "linked_route": "/sicurezza/cant_4c55c12507fb",
      "linked_label": "Apri scheda cantiere",
      "context": {
        "phase": "sicurezza",
        "gate_type": "soggetti"
      },
      "dedupe_key": "com_7295fcc4e93c|soggetti|cant_4c55c12507fb|MEDICO_COMPETENTE_MISSING",
      "created_at": "2026-03-22T17:47:28.660159+00:00",
      "updated_at": "2026-03-22T17:47:42.925976+00:00",
      "resolved_at": "2026-03-22T17:47:42.925976+00:00",
      "resolved_by": null,
      "resolution_note": "Chiuso automaticamente: condizione non piu presente nella fonte soggetti"
    },
    {
      "obbligo_id": "obl_3eb7a16c74e9",
      "user_id": "user_6988e9b9316c",
      "tenant_id": null,
      "commessa_id": "com_7295fcc4e93c",
      "cantiere_id": "cant_4c55c12507fb",
      "ramo_id": "",
      "emissione_id": "",
      "source_module": "soggetti",
      "source_entity_type": "cantiere_sicurezza",
      "source_entity_id": "cant_4c55c12507fb",
      "code": "PREPOSTO_CANTIERE_MISSING",
      "title": "Preposto Cantiere non indicato",
      "description": "Il ruolo obbligatorio 'Preposto Cantiere' non risulta compilato nella scheda cantiere.",
      "category": "sicurezza",
      "severity": "media",
      "severity_sort": 2,
      "blocking_level": "warning",
      "blocking_level_sort": 2,
      "status": "nuovo",
      "auto_generated": true,
      "owner_role": "sicurezza",
      "owner_user_id": null,
      "due_date": null,
      "linked_route": "/sicurezza/cant_4c55c12507fb",
      "linked_label": "Apri scheda cantiere",
      "context": {
        "phase": "sicurezza",
        "gate_type": "soggetti"
      },
      "dedupe_key": "com_7295fcc4e93c|soggetti|cant_4c55c12507fb|PREPOSTO_CANTIERE_MISSING",
      "created_at": "2026-03-22T17:47:28.660166+00:00",
      "updated_at": "2026-03-22T17:47:28.660166+00:00",
      "resolved_at": null,
      "resolved_by": null,
      "resolution_note": null
    }
  ]
}